__init__.py
cli/__init__.py
cli/__main__.py
templates/__init__.py
templates/advanced/Makefile
templates/advanced/README.md
templates/advanced/__init__.py
templates/advanced/main.py
templates/advanced/requirements.txt
templates/advanced/ruff.toml
templates/advanced/tests/__init__.py
templates/advanced/tests/test_main.py
templates/hello_world/.gitignore
templates/hello_world/Makefile
templates/hello_world/README.md
templates/hello_world/__init__.py
templates/hello_world/main.py
templates/hello_world/requirements.txt
templates/hello_world/tests/__init__.py
templates/hello_world/tests/test_main.py
templates/langchain/.gitignore
templates/langchain/Makefile
templates/langchain/README.md
templates/langchain/__init__.py
templates/langchain/main.py
templates/langchain/requirements.txt
templates/langchain/ruff.toml
templates/langchain/tests/__init__.py
templates/langchain/tests/test_main.py
templates/llama/.gitignore
templates/llama/Makefile
templates/llama/README.md
templates/llama/__init__.py
templates/llama/main.py
templates/llama/requirements.txt
templates/llama/ruff.toml
templates/llama/models/.gitkeep
templates/llama/tests/__init__.py
templates/llama/tests/test_main.py
templates/nlp/.gitignore
templates/nlp/Makefile
templates/nlp/README.md
templates/nlp/__init__.py
templates/nlp/conftest.py
templates/nlp/main.py
templates/nlp/requirements.txt
templates/nlp/ruff.toml
templates/nlp/tests/__init__.py
templates/nlp/tests/test_main.py
fastapi_gen-0.10.0.dist-info/METADATA
fastapi_gen-0.10.0.dist-info/WHEEL
fastapi_gen-0.10.0.dist-info/entry_points.txt
fastapi_gen-0.10.0.dist-info/licenses/LICENSE
fastapi_gen-0.10.0.dist-info/RECORD
