Metadata-Version: 2.4
Name: fastapi-gen
Version: 0.10.0
Summary: Set up a modern REST API by running one command.
Project-URL: Documentation, https://github.com/mirpo/fastapi-gen#readme
Project-URL: Issues, https://github.com/mirpo/fastapi-gen/issues
Project-URL: Source, https://github.com/mirpo/fastapi-gen
Author-email: Miroslav Pokrovskii <miroslavpokrovskiy@gmail.com>
License-Expression: MIT
License-File: LICENSE
Keywords: cli,fastapi,hello world,huggingface,langchain,llama,llama.cpp,named-entity recognition,ner,nlp,summarization,text generation
Classifier: Development Status :: 4 - Beta
Classifier: Environment :: Web Environment
Classifier: Framework :: AsyncIO
Classifier: Framework :: FastAPI
Classifier: Framework :: Pydantic
Classifier: Framework :: Pydantic :: 1
Classifier: Intended Audience :: Developers
Classifier: Intended Audience :: Information Technology
Classifier: Intended Audience :: System Administrators
Classifier: License :: OSI Approved :: MIT License
Classifier: Operating System :: OS Independent
Classifier: Programming Language :: Python
Classifier: Programming Language :: Python :: 3
Classifier: Programming Language :: Python :: 3 :: Only
Classifier: Programming Language :: Python :: 3.12
Classifier: Programming Language :: Python :: 3.13
Classifier: Topic :: Internet
Classifier: Topic :: Internet :: WWW/HTTP
Classifier: Topic :: Internet :: WWW/HTTP :: HTTP Servers
Classifier: Topic :: Scientific/Engineering :: Artificial Intelligence
Classifier: Topic :: Software Development
Classifier: Topic :: Software Development :: Libraries
Classifier: Topic :: Software Development :: Libraries :: Application Frameworks
Classifier: Topic :: Software Development :: Libraries :: Python Modules
Classifier: Typing :: Typed
Requires-Python: >=3.11
Requires-Dist: click==8.3.0
Requires-Dist: colorama==0.4.6
Requires-Dist: importlib-resources==6.5.2
Provides-Extra: dev
Requires-Dist: coverage[toml]==7.11.0; extra == 'dev'
Requires-Dist: pytest==8.4.2; extra == 'dev'
Requires-Dist: ruff==0.14.1; extra == 'dev'
